chartokenizer/__init__.py
chartokenizer/tokenizer.py
chartokenizer-1.0.0.dist-info/LICENSE
chartokenizer-1.0.0.dist-info/METADATA
chartokenizer-1.0.0.dist-info/WHEEL
chartokenizer-1.0.0.dist-info/top_level.txt
chartokenizer-1.0.0.dist-info/RECORD
