Metadata-Version: 2.1
Name: chartokenizer
Version: 1.0.0
Summary: A basic character-level tokenizer 
Home-page: https://github.com/MrTechyWorker/chartokenizer
Author: R Shashank Kanna
Author-email: techyworker420@gmail.com
Classifier: Programming Language :: Python :: 3
Classifier: License :: OSI Approved :: Apache Software License
Classifier: Operating System :: OS Independent
Requires-Python: >=3.6
License-File: LICENSE
